LICENSE
MANIFEST.in
README.md
setup.py
hpnapy/__init__.py
hpnapy/exceptions.py
hpnapy/hpnapy.py
hpnapy.egg-info/PKG-INFO
hpnapy.egg-info/SOURCES.txt
hpnapy.egg-info/dependency_links.txt
hpnapy.egg-info/requires.txt
hpnapy.egg-info/top_level.txt