Metadata-Version: 1.1
Name: hpnapy
Version: 1.0.4
Summary: HP Network automation framework
Home-page: https://github.com/spenceation/hpnapy
Author: Spencer Ervin
Author-email: spenceation@hotmail.com
License:                     GNU GENERAL PUBLIC LICENSE
